pydlock/__init__.py
pydlock/__main__.py
pydlock/constants.py
pydlock-1.2.0.15.dist-info/LICENSE
pydlock-1.2.0.15.dist-info/METADATA
pydlock-1.2.0.15.dist-info/WHEEL
pydlock-1.2.0.15.dist-info/top_level.txt
pydlock-1.2.0.15.dist-info/RECORD
