Metadata-Version: 2.1
Name: pydlock
Version: 1.2.0.15
Summary: A package for encrypting files with a password.
Home-page: https://www.github.com/ErickShepherd/pydlock
Author: Erick Edward Shepherd
Author-email: Contact@ErickShepherd.com
Maintainer: Erick Edward Shepherd
Maintainer-email: Contact@ErickShepherd.com
License: MIT
Download-URL: https://pypi.org/project/pydlock/
Project-URL: Bug Tracker, https://github.com/ErickShepherd/pydlock/issues
Project-URL: Source Code, https://github.com/ErickShepherd/pydlock
Project-URL: Documentation, https://github.com/ErickShepherd/pydlock/blob/master/README.rst
Platform: Windows
Platform: Linux
Platform: Solaris
Platform: Mac OS-X
Platform: Unix
Classifier: Intended Audience :: Developers
Classifier: Intended Audience :: End Users/Desktop
Classifier: Topic :: Security
Classifier: Environment :: Console
Classifier: Development Status :: 5 - Production/Stable
Classifier: Natural Language :: English
Classifier: Programming Language :: Python
Classifier: Programming Language :: Python :: 3
Classifier: Programming Language :: Python :: 3.7
Classifier: License :: OSI Approved :: MIT License
Classifier: Operating System :: Microsoft :: Windows
Classifier: Operating System :: POSIX
Classifier: Operating System :: Unix
Classifier: Operating System :: MacOS
Requires-Python: >=3.7
